[{"fecha":"2023-10-24T06:24:19.000Z","usuario":"asd@gmail.com","ISBN13":"9788423687572","titulo":"Software la Superbabosa","disponibilidad":1,"fechaentrega":"2023-11-23T06:24:19.000Z","portada":"https://images.cdn2.buscalibre.com/fit-in/180x180/1f/a6/1fa666e0f93fb0bc63c4c214188f3a46.jpg"},{"fecha":"2023-11-23T06:24:30.000Z","usuario":"asd@gmail.com","ISBN13":"9789563962642","titulo":"Reemplazada por un Software","disponibilidad":1,"fechaentrega":"2023-12-23T06:24:30.000Z","portada":"https://images.cdn3.buscalibre.com/fit-in/180x180/a0/b2/a0b2c729a04d61a9348942dff8dbaa39.jpg"},{"fecha":"2023-10-26T06:28:05.000Z","usuario":"asd@gmail.com","ISBN13":"9781107646377","titulo":"objective proficiency st+key+downloadble software","disponibilidad":1,"fechaentrega":"2023-11-25T06:28:05.000Z","portada":"https://images.cdn2.buscalibre.com/fit-in/180x180/89/23/8923d9b63c70b3405ea078b840a75416.jpg"},{"fecha":"2023-11-01T18:40:38.000Z","usuario":"micorreo32@hotmail.com","ISBN13":"9781913597412","titulo":"Arquitectura Limpia: Consejos y Trucos Para el Software y la Programación Utilizando Teorías de Arquitectura Limpia","disponibilidad":1,"fechaentrega":"2023-12-01T18:40:38.000Z","portada":"https://images.cdn1.buscalibre.com/fit-in/180x180/8f/4d/8f4df526da963550fe30313534195473.jpg"}]