[{"nombres":"Fernando","apellidos":"Zuasnabar","tipoDocumento":"DNI","nroDocumento":"75471799","correo":"fer@gmail.com","password":"fer123","repetirPassword":"fer123"},{"nombres":"fernando1","apellidos":"zuasnabar1","tipoDocumento":"DNI","nroDocumento":"12515138","correo":"fer1@gmail.com","password":"fer123","repetirPassword":"fer123"},{"nombres":"fernando2","apellidos":"zuasnabar2","tipoDocumento":"DNI","nroDocumento":"12345678","correo":"fer2@gmail.com","password":"fer123","repetirPassword":"fer123"},{"nombres":"fer3","apellidos":"zuasnabar3","tipoDocumento":"dni","nroDocumento":"132041248","correo":"fer3@gmail.com","password":"fer123","repetirPassword":"fer123"},{"nombres":"fernando4","apellidos":"zuasnabar4","tipoDocumento":"dni","nroDocumento":"15213564","correo":"fer4@gmail.com","password":"fer123","repetirPassword":"fer123"}]
